redicms/__init__.py
redicms/db/__init__.py
redicms/db/models/__init__.py
redicms/db/models/fields.py
RediCMS-0.3.0.dist-info/LICENSE
RediCMS-0.3.0.dist-info/METADATA
RediCMS-0.3.0.dist-info/WHEEL
RediCMS-0.3.0.dist-info/top_level.txt
RediCMS-0.3.0.dist-info/RECORD
