Metadata-Version: 2.1
Name: RediCMS
Version: 0.3.0
Author: Anvish Inc.
Author-email: "Anvish Inc." <anvish@anvish.in>
License: CC-BY-NC-ND-4.0
Classifier: Development Status :: 3 - Alpha
Classifier: Framework :: Django
Classifier: Programming Language :: Python :: 3.12
Classifier: License :: Other/Proprietary License
Requires-Python: >=3.12
License-File: LICENSE
Requires-Dist: django>=5.1.3
Requires-Dist: djangorestframework>=3.15.2
